sail/__init__.py
sail/tensor.py
sail/dtype.py
sail/_sail_docs.py
sail/csrc/libsail_c.so
sail/csrc/__init__.py
sail_ml.libs/libblas-8d819fb1.so.3.2.1
sail_ml.libs/libboost_program_options-mt-33c4eeb7.so.5
sail_ml.libs/libgfortran-139be63a.so.3.0.0
sail_ml-0.0.1a1.dist-info/top_level.txt
sail_ml-0.0.1a1.dist-info/LICENSE
sail_ml-0.0.1a1.dist-info/METADATA
sail_ml-0.0.1a1.dist-info/RECORD
sail_ml-0.0.1a1.dist-info/WHEEL
