Metadata-Version: 2.1
Name: sail-ml
Version: 0.0.1a1
Summary: SAIL: Simple AI Library
Home-page: UNKNOWN
Author: Tucker Siegel
Author-email: tgsiegel@umd.edu
License: UNKNOWN
Platform: UNKNOWN
License-File: LICENSE
Requires-Dist: numpy (>=1.19.5)
